fp_th_di_mail_sender/__init__.py
fp_th_di_mail_sender/mail_sender.py
fp_th_di_mail_sender-1.0.0.dist-info/METADATA
fp_th_di_mail_sender-1.0.0.dist-info/WHEEL
fp_th_di_mail_sender-1.0.0.dist-info/top_level.txt
fp_th_di_mail_sender-1.0.0.dist-info/RECORD
