Metadata-Version: 2.1
Name: fp_th_di_mail_sender
Version: 1.0.0
Summary: Foodpanda Thailand Data & Insight team - Utility function for mail sending using SMTP
Home-page: UNKNOWN
Author: Mathara Rojanamontien
Author-email: mathara.rojanamontien@foodpanda.co.th
License: Delivery Hero (Thailand) Co., Ltd.
Platform: UNKNOWN
